{"schema":5,"addons":[{"id":"langpack-ko@firefox.mozilla.org","icons":{"32":null,"64":null},"name":"Korean (KR) Language Pack","type":"locale","version":"57.0","repositoryStatus":4,"creator":{"name":"Mozilla","url":"https://addons.mozilla.org/ko/firefox/user/mozilla/?src=api"},"description":"Korean (KR) Language Pack","fullDescription":null,"isPlatformCompatible":true,"eula":null,"averageRating":5,"learnmoreURL":"https://addons.mozilla.org/ko/firefox/addon/korean-kr-language-pack/?src=api","homepageURL":"https://addons.mozilla.org/ko/firefox/addon/korean-kr-language-pack/?src=api","sourceURI":"https://addons.mozilla.org/firefox/downloads/file/770928/korean_kr_language_pack-57.0-fx.xpi?src=api","size":507907,"developerComments":null,"reviewURL":"https://addons.mozilla.org/ko/firefox/addon/korean-kr-language-pack/reviews/?src=api","reviewCount":2,"totalDownloads":36021,"weeklyDownloads":127,"dailyUsers":36021,"updateDate":1510657198000,"supportURL":null}]}